<?xml version="1.0" encoding="UTF-8" standalone="no"?><Pedidos>
<Pedido id="122"><proveedor>32</proveedor><nombre>Entrepinares</nombre><producto>Queso semicurado</producto><cantidad>50</cantidad><precio>220.67</precio></Pedido><Pedido id="122"><proveedor>32</proveedor><nombre>Entrepinares</nombre><producto>Queso semicurado</producto><cantidad>50</cantidad><precio>220.67</precio></Pedido><Pedido id="122"><proveedor>32</proveedor><nombre>Entrepinares</nombre><producto>Queso semicurado</producto><cantidad>50</cantidad><precio>220.67</precio></Pedido><Pedido id="122"><proveedor>32</proveedor><nombre>Entrepinares</nombre><producto>Queso semicurado</producto><cantidad>50</cantidad><precio>220.67</precio></Pedido><Pedido id="122"><proveedor>32</proveedor><nombre>Entrepinares</nombre><producto>Queso semicurado</producto><cantidad>50</cantidad><precio>220.67</precio></Pedido></Pedidos>